valids/__about__.py
valids/__init__.py
valids/base.py
valids/exceptions.py
valids/factory.py
valids/typing.py
valids/validators/__init__.py
valids/validators/boolean.py
valids/validators/numeric.py
valids/validators/string.py
valids-0.1.2.dist-info/METADATA
valids-0.1.2.dist-info/WHEEL
valids-0.1.2.dist-info/licenses/LICENSE.txt
valids-0.1.2.dist-info/RECORD
